s3m.py
s3m-1.1.0.dist-info/METADATA
s3m-1.1.0.dist-info/RECORD
s3m-1.1.0.dist-info/WHEEL
s3m-1.1.0.dist-info/top_level.txt
