Metadata-Version: 2.1
Name: s3m
Version: 1.1.0
Summary: sqlite3 wrapper for multithreaded applications
Home-page: https://github.com/ivknv/s3m
Author: Ivan Konovalov
Author-email: ivknv0@gmail.com
License: LGPLv3
Project-URL: Source code, https://github.com/ivknv/s3m
Project-URL: Documentation, https://s3m.readthedocs.io
Keywords: sqlite3 sqlite multithreading thread
Platform: UNKNOWN
Classifier: Development Status :: 4 - Beta
Classifier: Intended Audience :: Developers
Classifier: License :: OSI Approved :: GNU Lesser General Public License v3 (LGPLv3)
Classifier: License :: OSI Approved :: GNU Lesser General Public License v3 or later (LGPLv3+)
Classifier: Programming Language :: Python
Classifier: Programming Language :: Python :: 3
Classifier: Topic :: Database
Classifier: Topic :: Software Development :: Libraries
Classifier: Topic :: Software Development :: Libraries :: Python Modules
Requires-Python: >=3
